Workbook

Sheet Carátula EP N°1 (15%)
A1: ESTADO DE PAGO N° 1 (AVANCE FÍSICO 15%)
A2: CONSTRUCCIÓN EDIFICIO DE BODEGAS BSL QUILICURA — GRUPO 7
A4: MANDANTE / PROPIETARIO | C4: BSL Inversiones Industriales S.A.
A5: CONTRATISTA | C5: Constructora Grupo 7 — Oscar Rodríguez & Nicolás Letelier
A6: UBICACIÓN | C6: Calle Meulén N°331 (ex 451), Lote F, Quilicura, Santiago
A7: FECHA DE CORTE DEL AVANCE | C7: 30 de abril de 2026
A8: FECHA DE PRESENTACIÓN EP | C8: 08 de mayo de 2026 (mes siguiente)
A9: PERÍODO DEL ESTADO DE PAGO | C9: 02 de marzo de 2026 al 30 de abril de 2026
A10: PLAZO CONTRACTUAL | C10: 193 días hábiles (Marzo a Diciembre 2026)
A11: PORCENTAJE AVANCE FÍSICO ACUMULADO | C11: 15.03%
A12: MONTO TOTAL CONTRATO (sin IVA) | C12: $ 5,758,410,689
A14: LIQUIDACIÓN ECONÓMICA Y APLICACIÓN DE REAJUSTE IPC (BASE ENERO 2026)
A15: 1. Monto Básico Acumulado Ejecutado a la Fecha (sin IVA) | C15: ='Detalle EP N°1'!H48
A16: 2. Menos Monto Básico Estado de Pago Anterior | C16: 0
A17: 3. Monto Básico Líquido del Período | C17: =C15-C16
A18: --- REAJUSTE POR ÍNDICE DE PRECIOS AL CONSUMIDOR (IPC) ---
A19: - IPC Mes Base (Enero 2026) | C19: 109.71
A20: - IPC Mes Cierre Avance (Abril 2026) | C20: 112.18
A21: - Factor Reajuste Cierre (IPC Abr / IPC Ene) | C21: =112.18/109.71
A22: - IPC Mes Presentación (Mayo 2026 - habitual mes siguiente) | C22: 112.37
A23: - Factor Reajuste Presentación (IPC May / IPC Ene) | C23: =112.37/109.71
A24: 4. Reajuste IPC del Período (según mes presentación Mayo 2026: +2.42%) | C24: =C17*(C23-1)
A25: 5. Monto Líquido del Período con Reajuste IPC (3 + 4) | C25: =C17+C24
A26: --- DESCUENTOS Y RETENCIONES CONTRACTUALES ---
A27: 6. Retención de Garantía Contractual (5.0% sobre Monto con Reajuste) | C27: =C25*0.05
A28: 7. Devolución de Anticipo (si aplica) | C28: 0
A29: 8. TOTAL LÍQUIDO A FACTURAR EN EL PERÍODO (sin IVA) (5 - 6 - 7) | C29: =C25-C27-C28
A30: 9. Impuesto al Valor Agregado (IVA 19%) | C30: =C29*0.19
A31: 10. TOTAL A PAGAR ESTADO DE PAGO N° 1 (con IVA) | C31: =C29+C30

Sheet Detalle EP N°1
A1: DETALLE DE PARTIDAS EJECUTADAS — ESTADO DE PAGO N° 1 (15% AVANCE)
A2: Fecha de Corte: 30 de abril de 2026 | Valores en CLP (Costo Directo + GG 15.27% + Utilidad 9.00%)
A4: Ítem | B4: Descripción de la Partida | C4: Unid. | D4: Cantidad Contrato | E4: PU Venta ($) | F4: Cant. Acum. Anterior | G4: Cant. Presente Período | H4: Monto Presente Período ($) | I4: % Avance Partida | J4: Saldo por Ejecutar
A5: 1.1 | B5: Excavación en TCN Caminos | C5: m3 | D5: 466 | E5: 6834.8775 | F5: 0 | G5: 466 | H5: =G5*E5 | I5: =G5/D5 | J5: =D5-G5
A6: 1.2 | B6: Excavación en TCN Bodegas | C6: m3 | D6: 20354 | E6: 6834.8775 | F6: 0 | G6: 20354 | H6: =G6*E6 | I6: =G6/D6 | J6: =D6-G6
A7: 1.3 | B7: Mejoramiento Fundaciones con integral natural (1,5 m.) | C7: m3 | D7: 7740 | E7: 22368.69 | F7: 0 | G7: 7740 | H7: =G7*E7 | I7: =G7/D7 | J7: =D7-G7
A8: 1.4 | B8: Mejoramiento Fundaciones con integral natural (0,5 m.) | C8: m3 | D8: 2944 | E8: 22368.69 | F8: 0 | G8: 2944 | H8: =G8*E8 | I8: =G8/D8 | J8: =D8-G8
A9: 1.5 | B9: Relleno Estructural bajo 2" (Fundaciones a Subrasante) | C9: m3 | D9: 2198 | E9: 24854.1 | F9: 0 | G9: 0 | H9: =G9*E9 | I9: =G9/D9 | J9: =D9-G9
A10: 1.6 | B10: Relleno Estructural bajo 6" (Fundaciones a Subrasante) | C10: m3 | D10: 3299 | E10: 24854.1 | F10: 0 | G10: 0 | H10: =G10*E10 | I10: =G10/D10 | J10: =D10-G10
A11: 1.7 | B11: Relleno Estructural bajo 2" Bodegas, Oficinas, VF | C11: m3 | D11: 3398 | E11: 24854.1 | F11: 0 | G11: 0 | H11: =G11*E11 | I11: =G11/D11 | J11: =D11-G11
A12: 1.8 | B12: Terraplén caminos y areas de servicio | C12: m3 | D12: 1955 | E12: 6213.525 | F12: 0 | G12: 1955 | H12: =G12*E12 | I12: =G12/D12 | J12: =D12-G12
A13: 1.9 | B13: Terraplén bajo radier bodegas | C13: m3 | D13: 1699 | E13: 6213.525 | F13: 0 | G13: 0 | H13: =G13*E13 | I13: =G13/D13 | J13: =D13-G13
A14: 1.10 | B14: Preparación de la Subrasante Bodegas | C14: m2 | D14: 16024 | E14: 1864.0575 | F14: 0 | G14: 13734.857 | H14: =G14*E14 | I14: =G14/D14 | J14: =D14-G14
A15: 1.11 | B15: Preparación de la Subrasante Caminos y Areas de Servicio | C15: m2 | D15: 9756 | E15: 1864.0575 | F15: 0 | G15: 9756 | H15: =G15*E15 | I15: =G15/D15 | J15: =D15-G15
A16: 1.12 | B16: Base Granular Caminos | C16: m3 | D16: 1965 | E16: 26718.158 | F16: 0 | G16: 1965 | H16: =G16*E16 | I16: =G16/D16 | J16: =D16-G16
... A45: 2.14 | B45: Cierre perimetral Bulldog | C45: ml | D45: 364 | E45: 64620.66 | F45: 0 | G45: 364 | H45: =G45*E45 | I45: =G45/D45 | J45: =D45-G45
A46: TOTAL EJECUTADO ESTADO DE PAGO N° 1 (sin IVA) | H46: =SUM(H5:H45) | I46: =H46/5758410688.804201

Sheet Carátula EP N°2 (35%)
A1: ESTADO DE PAGO N° 2 (AVANCE FÍSICO 35%)
A2: CONSTRUCCIÓN EDIFICIO DE BODEGAS BSL QUILICURA — GRUPO 7
A4: MANDANTE / PROPIETARIO | C4: BSL Inversiones Industriales S.A.
A5: CONTRATISTA | C5: Constructora Grupo 7 — Oscar Rodríguez & Nicolás Letelier
A6: UBICACIÓN | C6: Calle Meulén N°331 (ex 451), Lote F, Quilicura, Santiago
A7: FECHA DE CORTE DEL AVANCE | C7: 16 de junio de 2026
A8: FECHA DE PRESENTACIÓN EP | C8: 24 de junio de 2026 (mes siguiente / liquidación)
A9: PERÍODO DEL ESTADO DE PAGO | C9: 01 de mayo de 2026 al 16 de junio de 2026
A10: PLAZO CONTRACTUAL | C10: 193 días hábiles (Marzo a Diciembre 2026)
A11: PORCENTAJE AVANCE FÍSICO ACUMULADO | C11: 35.35%
A12: MONTO TOTAL CONTRATO (sin IVA) | C12: $ 5,758,410,689
A14: LIQUIDACIÓN ECONÓMICA Y APLICACIÓN DE REAJUSTE IPC (BASE ENERO 2026)
A15: 1. Monto Básico Acumulado Ejecutado a la Fecha (sin IVA) | C15: ='Detalle EP N°2'!I48
A16: 2. Menos Monto Básico Acumulado Estado de Pago N° 1 | C16: ='Carátula EP N°1 (15%)'!C15
A17: 3. Monto Básico Líquido del Presente Período N° 2 | C17: =C15-C16
A18: --- REAJUSTE POR ÍNDICE DE PRECIOS AL CONSUMIDOR (IPC) ---
A19: - IPC Mes Base (Enero 2026) | C19: 109.71
A20: - IPC Mes Cierre Avance (Junio 2026) | C20: 112.35
A21: - Factor Reajuste Cierre (IPC Jun / IPC Ene) | C21: =112.35/109.71
A22: - IPC Mes Presentación (Julio 2026 - habitual mes siguiente) | C22: 112.45
A23: - Factor Reajuste Presentación (IPC Jul / IPC Ene) | C23: =112.45/109.71
A24: 4. Reajuste IPC del Período (según mes presentación Julio 2026: +2.50%) | C24: =C17*(C23-1)
A25: 5. Monto Líquido del Período con Reajuste IPC (3 + 4) | C25: =C17+C24
A26: --- DESCUENTOS Y RETENCIONES CONTRACTUALES ---
A27: 6. Retención de Garantía Contractual (5.0% sobre Monto con Reajuste) | C27: =C25*0.05
A28: 7. Devolución de Anticipo (si aplica) | C28: 0
A29: 8. TOTAL LÍQUIDO A FACTURAR EN EL PERÍODO N° 2 (sin IVA) (5 - 6 - 7) | C29: =C25-C27-C28
A30: 9. Impuesto al Valor Agregado (IVA 19%) | C30: =C29*0.19
A31: 10. TOTAL A PAGAR ESTADO DE PAGO N° 2 (con IVA) | C31: =C29+C30

Sheet Detalle EP N°2
A1: DETALLE DE PARTIDAS EJECUTADAS — ESTADO DE PAGO N° 2 (35% AVANCE)
A2: Fecha de Corte: 16 de junio de 2026 | Valores en CLP (Costo Directo + GG 15.27% + Utilidad 9.00%)
A4: Ítem | B4: Descripción de la Partida | C4: Unid. | D4: Cantidad Contrato | E4: PU Venta ($) | F4: Cant. Acum. Anterior (EP1) | G4: Cant. Presente Período | H4: Cant. Acumulada a la Fecha | I4: Monto Acumulado a la Fecha ($) | J4: % Avance Partida | K4: Saldo por Ejecutar
A5: 1.1 | B5: Excavación en TCN Caminos | C5: m3 | D5: 466 | E5: 6834.8775 | F5: ='Detalle EP N°1'!G5 | G5: 0 | H5: =F5+G5 | I5: =H5*E5 | J5: =H5/D5 | K5: =D5-H5
A6: 1.2 | B6: Excavación en TCN Bodegas | C6: m3 | D6: 20354 | E6: 6834.8775 | F6: ='Detalle EP N°1'!G6 | G6: 0 | H6: =F6+G6 | I6: =H6*E6 | J6: =H6/D6 | K6: =D6-H6
A7: 1.3 | B7: Mejoramiento Fundaciones con integral natural (1,5 m.) | C7: m3 | D7: 7740 | E7: 22368.69 | F7: ='Detalle EP N°1'!G7 | G7: 0 | H7: =F7+G7 | I7: =H7*E7 | J7: =H7/D7 | K7: =D7-H7
A8: 1.4 | B8: Mejoramiento Fundaciones con integral natural (0,5 m.) | C8: m3 | D8: 2944 | E8: 22368.69 | F8: ='Detalle EP N°1'!G8 | G8: 0 | H8: =F8+G8 | I8: =H8*E8 | J8: =H8/D8 | K8: =D8-H8
A9: 1.5 | B9: Relleno Estructural bajo 2" (Fundaciones a Subrasante) | C9: m3 | D9: 2198 | E9: 24854.1 | F9: ='Detalle EP N°1'!G9 | G9: 2198 | H9: =F9+G9 | I9: =H9*E9 | J9: =H9/D9 | K9: =D9-H9
A10: 1.6 | B10: Relleno Estructural bajo 6" (Fundaciones a Subrasante) | C10: m3 | D10: 3299 | E10: 24854.1 | F10: ='Detalle EP N°1'!G10 | G10: 3299 | H10: =F10+G10 | I10: =H10*E10 | J10: =H10/D10 | K10: =D10-H10
A11: 1.7 | B11: Relleno Estructural bajo 2" Bodegas, Oficinas, VF | C11: m3 | D11: 3398 | E11: 24854.1 | F11: ='Detalle EP N°1'!G11 | G11: 1456.2857 | H11: =F11+G11 | I11: =H11*E11 | J11: =H11/D11 | K11: =D11-H11
A12: 1.8 | B12: Terraplén caminos y areas de servicio | C12: m3 | D12: 1955 | E12: 6213.525 | F12: ='Detalle EP N°1'!G12 | G12: 0 | H12: =F12+G12 | I12: =H12*E12 | J12: =H12/D12 | K12: =D12-H12
A13: 1.9 | B13: Terraplén bajo radier bodegas | C13: m3 | D13: 1699 | E13: 6213.525 | F13: ='Detalle EP N°1'!G13 | G13: 1699 | H13: =F13+G13 | I13: =H13*E13 | J13: =H13/D13 | K13: =D13-H13
A14: 1.10 | B14: Preparación de la Subrasante Bodegas | C14: m2 | D14: 16024 | E14: 1864.0575 | F14: ='Detalle EP N°1'!G14 | G14: 2289.1429 | H14: =F14+G14 | I14: =H14*E14 | J14: =H14/D14 | K14: =D14-H14
A15: 1.11 | B15: Preparación de la Subrasante Caminos y Areas de Servicio | C15: m2 | D15: 9756 | E15: 1864.0575 | F15: ='Detalle EP N°1'!G15 | G15: 0 | H15: =F15+G15 | I15: =H15*E15 | J15: =H15/D15 | K15: =D15-H15
A16: 1.12 | B16: Base Granular Caminos | C16: m3 | D16: 1965 | E16: 26718.158 | F16: ='Detalle EP N°1'!G16 | G16: 0 | H16: =F16+G16 | I16: =H16*E16 | J16: =H16/D16 | K16: =D16-H16
... A45: 2.14 | B45: Cierre perimetral Bulldog | C45: ml | D45: 364 | E45: 64620.66 | F45: ='Detalle EP N°1'!G45 | G45: 0 | H45: =F45+G45 | I45: =H45*E45 | J45: =H45/D45 | K45: =D45-H45
A46: TOTAL ACUMULADO EJECUTADO A LA FECHA (sin IVA) | I46: =SUM(I5:I45) | J46: =I46/5758410688.804201
